unic/__init__.py
unic/configs/metirc_system/settings.toml
unic/configs/timeunit/settings.toml
unic/configs/timezone/settings.toml
unic/core/__init__.py
unic/core/base_model.py
unic/length_unit/constants/constants.py
unic/length_unit/exceptions/exceptions.py
unic/length_unit/metric_system/__init__.py
unic/length_unit/metric_system/metric_system_model.py
unic/length_unit/validators/__init__.py
unic/length_unit/validators/models.py
unic/length_unit/validators/validators.py
unic/time_unit/constants/constants.py
unic/time_unit/datetime/__init__.py
unic/time_unit/datetime/datetime_model.py
unic/time_unit/exceptions/exceptions.py
unic/time_unit/time/__init__.py
unic/time_unit/time/time_model.py
unic/time_unit/unixtime/__init__.py
unic/time_unit/unixtime/unixtime_model.py
unic/time_unit/validators/__init__.py
unic/time_unit/validators/models.py
unic/time_unit/validators/validators.py
unic/utils/__init__.py
unic/utils/config_parser.py
unic/utils/time_helpers.py
unic-2.2.0.dist-info/METADATA
unic-2.2.0.dist-info/WHEEL
unic-2.2.0.dist-info/licenses/LICENSE
unic-2.2.0.dist-info/RECORD
