Metadata-Version: 2.4
Name: unic
Version: 2.2.0
Summary: Python package for converting various units.
Project-URL: Repository, https://github.com/subretu/unic
Author: Subretu
Maintainer: Subretu
License-Expression: MIT
License-File: LICENSE
Keywords: convert,length,time,timestamp,unit
Classifier: License :: OSI Approved :: MIT License
Classifier: Programming Language :: Python :: 3.9
Classifier: Programming Language :: Python :: 3.10
Classifier: Programming Language :: Python :: 3.11
Classifier: Programming Language :: Python :: 3.12
Classifier: Programming Language :: Python :: 3.13
Classifier: Programming Language :: Python :: 3.14
Requires-Python: <4,>=3.9.0
Requires-Dist: pydantic~=2.1
Requires-Dist: tomli<2.4.0,>=2.0.1
